AUTHORS
LICENSE
MANIFEST.in
README.rst
setup.cfg
setup.py
./requirements-base.txt
./requirements-dev.txt
./requirements-optional.txt
./requirements-test.txt
./examples/oauth2_consumer_webserver/requirements.txt
src/bitfield/__init__.py
src/bitfield/admin.py
src/bitfield/apps.py
src/bitfield/compat.py
src/bitfield/forms.py
src/bitfield/models.py
src/bitfield/query.py
src/bitfield/types.py
src/debug_toolbar/__init__.py
src/debug_toolbar/apps.py
src/debug_toolbar/compat.py
src/debug_toolbar/middleware.py
src/debug_toolbar/models.py
src/debug_toolbar/settings.py
src/debug_toolbar/toolbar.py
src/debug_toolbar/utils.py
src/debug_toolbar/views.py
src/debug_toolbar/management/__init__.py
src/debug_toolbar/management/commands/__init__.py
src/debug_toolbar/management/commands/debugsqlshell.py
src/debug_toolbar/panels/__init__.py
src/debug_toolbar/panels/cache.py
src/debug_toolbar/panels/headers.py
src/debug_toolbar/panels/logging.py
src/debug_toolbar/panels/profiling.py
src/debug_toolbar/panels/redirects.py
src/debug_toolbar/panels/request.py
src/debug_toolbar/panels/settings.py
src/debug_toolbar/panels/signals.py
src/debug_toolbar/panels/staticfiles.py
src/debug_toolbar/panels/timer.py
src/debug_toolbar/panels/versions.py
src/debug_toolbar/panels/sql/__init__.py
src/debug_toolbar/panels/sql/forms.py
src/debug_toolbar/panels/sql/panel.py
src/debug_toolbar/panels/sql/tracking.py
src/debug_toolbar/panels/sql/utils.py
src/debug_toolbar/panels/sql/views.py
src/debug_toolbar/panels/templates/__init__.py
src/debug_toolbar/panels/templates/panel.py
src/debug_toolbar/panels/templates/views.py
src/debug_toolbar/templatetags/__init__.py
src/debug_toolbar/templatetags/compat.py
src/sentry/__init__.py
src/sentry/__main__.py
src/sentry/admin.py
src/sentry/app.py
src/sentry/assets.json
src/sentry/celery.py
src/sentry/constants.py
src/sentry/coreapi.py
src/sentry/django_admin.py
src/sentry/event_manager.py
src/sentry/exceptions.py
src/sentry/http.py
src/sentry/monkey.py
src/sentry_nos.egg-info/PKG-INFO
src/sentry_nos.egg-info/SOURCES.txt
src/sentry_nos.egg-info/dependency_links.txt
src/sentry_nos.egg-info/entry_points.txt
src/sentry_nos.egg-info/not-zip-safe
src/sentry_nos.egg-info/requires.txt
src/sentry_nos.egg-info/top_level.txt
